{"metadata": [{"Translator": "Hall, J. Lesslie (John Lesslie), 1856-1928", "Title": "Beowulf: An Anglo-Saxon Epic Poem", "Note": "Translated From The Heyne-Socin Text by Lesslie Hall", "Language": "English", "LoC Class": "PR: Language and Literatures: English literature", "Subject": "Dragons -- Poetry", "Category": "Text", "EBook-No.": "16328", "Release Date": "Jul 19, 2005", "Copyright Status": "Public domain in the USA.", "Downloads": "9056 downloads in the last 30 days.", "Price": "$0.00", "file_link": "https://www.gutenberg.org/files/16328/16328-0.txt", "filename": "John Lesslie Hall - Beowulf: An Anglo-Saxon Epic Poem"}, {"Author": "Whitman, Walt, 1819-1892", "Title": "Leaves of Grass", "Language": "English", "LoC Class": "PS: Language and Literatures: American and Canadian literature", "Subject": "American poetry -- 19th century", "Category": "Text", "EBook-No.": "1322", "Release Date": "May 1, 1998", "Copyright Status": "Public domain in the USA.", "Downloads": "3830 downloads in the last 30 days.", "Price": "$0.00", "file_link": "https://www.gutenberg.org/files/1322/1322-0.txt", "filename": "Walt Whitman - Leaves of Grass"}, {"Author": "Wordsworth, William, 1770-1850", "Title": "Lyrical Ballads, With a Few Other Poems (1798)", "Language": "English", "LoC Class": "PR: Language and Literatures: English literature", "Subject": "English poetry -- 18th century", "Category": "Text", "EBook-No.": "9622", "Release Date": "Jan 1, 2006", "Copyright Status": "Public domain in the USA.", "Downloads": "3040 downloads in the last 30 days.", "Price": "$0.00", "file_link": "https://www.gutenberg.org/ebooks/9622.txt.utf-8", "filename": "William Wordsworth - Lyrical Ballads, With a Few Other Poems (1798)"}, {"Author": "Milton, John, 1608-1674", "Title": "Paradise Lost", "Note": "See also #26, which is from a substantially different print edition. #20 has 10 books, while #26 has 12 books.", "Language": "English", "LoC Class": "PR: Language and Literatures: English literature", "Subject": "Bible. Genesis -- History of Biblical events -- Poetry", "Category": "Text", "EBook-No.": "20", "Release Date": "Oct 1, 1991", "Copyright Status": "Public domain in the USA.", "Downloads": "2540 downloads in the last 30 days.", "Price": "$0.00", "file_link": "https://www.gutenberg.org/files/20/20-0.txt", "filename": "John Milton - Paradise Lost"}, {"Author": "Eliot, T. S. (Thomas Stearns), 1888-1965", "Title": "The Waste Land", "Language": "English", "LoC Class": "PS: Language and Literatures: American and Canadian literature", "Subject": "Prose poems", "Category": "Text", "EBook-No.": "1321", "Release Date": "May 1, 1998", "Copyright Status": "Public domain in the USA.", "Downloads": "2011 downloads in the last 30 days.", "Price": "$0.00", "file_link": "https://www.gutenberg.org/files/1321/1321-0.txt", "filename": "Thomas Stearns Eliot - The Waste Land"}, {"Author": "Virgil, 70 BCE-19 BCE", "Translator": "Dryden, John, 1631-1700", "Uniform Title": "Aeneis. English", "Title": "The Aeneid", "Language": "English", "LoC Class": "PA: Language and Literatures: Classical Languages and Literature", "Subject": "Epic poetry, Latin -- Translations into English", "Category": "Text", "EBook-No.": "228", "Release Date": "Mar 1, 1995", "Copyright Status": "Public domain in the USA.", "Downloads": "1842 downloads in the last 30 days.", "Price": "$0.00", "file_link": "https://www.gutenberg.org/files/228/228-0.txt", "filename": "John Dryden - The Aeneid"}, {"Author": "Keats, John, 1795-1821", "Title": "Lamia", "Language": "English", "LoC Class": "PR: Language and Literatures: English literature", "Subject": "English poetry -- 19th century", "Category": "Text", "EBook-No.": "2490", "Release Date": "Jan 1, 2001", "Copyright Status": "Public domain in the USA.", "Downloads": "1415 downloads in the last 30 days.", "Price": "$0.00", "file_link": "https://www.gutenberg.org/ebooks/2490.txt.utf-8", "filename": "John Keats - Lamia"}, {"Annotator": "Dwight, M. A. (Mary Ann), 1806-1858", "Author": "Homer, 750? BCE-650? BCE", "Editor": "Southey, Robert, 1774-1843", "Translator": "Cowper, William, 1731-1800", "Title": "The Iliad of Homer\rTranslated into English Blank Verse by William Cowper", "Imprint": "New York, D. Appleton & Co., 346 & 348 Broadway, 1860", "Note": "Project Gutenberg has several editions of this eBook:\r#22382  (With 800 linked footnotes)\r#16452  (In blank verse, Many footnotes.)\r#2199   (No footnotes or illustrations)\r#6130   (Many line drawings, and 300 footnotes)\r#3059   (Text file)\r#6150   (Text file)", "Credits": "Produced by Ted Garvin, Melissa Er-Raqabi, Fred Robinson and the Online Distributed Proofreading Team at http://www.pgdp.net", "Language": "English", "LoC Class": "PA: Language and Literatures: Classical Languages and Literature", "Subject": "Trojan War -- Poetry", "Category": "Text", "EBook-No.": "16452", "Release Date": "Aug 5, 2005", "Copyright Status": "Public domain in the USA.", "Downloads": "1022 downloads in the last 30 days.", "Price": "$0.00", "file_link": "https://www.gutenberg.org/files/16452/16452-0.txt", "filename": "Robert Southey - The Iliad of Homer\rTranslated into English Blank Verse by William Cowper"}, {"Editor": "Morris, Richard, 1833-1894", "Uniform Title": "Gawain and the Grene Knight", "Title": "Sir Gawayne and the Green KnightAn Alliterative Romance-Poem (c. 1360 A.D.)", "Language": "Middle English", "LoC Class": "PR: Language and Literatures: English literature", "Subject": "Gawain (Legendary character) -- Romances", "Category": "Text", "EBook-No.": "14568", "Release Date": "Jan 3, 2005", "Copyright Status": "Public domain in the USA.", "Downloads": "877 downloads in the last 30 days.", "Price": "$0.00", "file_link": "https://www.gutenberg.org/ebooks/14568.txt.utf-8", "filename": "Richard Morris - Sir Gawayne and the Green KnightAn Alliterative Romance-Poem (c. 1360 A.D.)"}, {"Author": "Keats, John, 1795-1821", "Editor": "Robertson, M. (Margaret)", "Title": "Keats: Poems Published in 1820", "Language": "English", "LoC Class": "PR: Language and Literatures: English literature", "Subject": "English poetry -- 19th century", "Category": "Text", "EBook-No.": "23684", "Release Date": "Dec 2, 2007", "Copyright Status": "Public domain in the USA.", "Downloads": "834 downloads in the last 30 days.", "Price": "$0.00", "file_link": "https://www.gutenberg.org/ebooks/23684.txt.utf-8", "filename": "Margaret Robertson - Keats: Poems Published in 1820"}, {"Author": "Eliot, T. S. (Thomas Stearns), 1888-1965", "LoC No.": "20004200 ", "Title": "Poems", "Language": "English", "LoC Class": "PS: Language and Literatures: American and Canadian literature", "Subject": "Poetry", "Category": "Text", "EBook-No.": "1567", "Release Date": "Dec 1, 1998", "Copyright Status": "Public domain in the USA.", "Downloads": "777 downloads in the last 30 days.", "Price": "$0.00", "file_link": "https://www.gutenberg.org/ebooks/1567.txt.utf-8", "filename": "Thomas Stearns Eliot - Poems"}, {"Author": "Dante Alighieri, 1265-1321", "Title": "La Divina Commedia di Dante", "Language": "Italian", "LoC Class": "PQ: Language and Literatures: Romance literatures: French, Italian, Spanish, Portuguese", "Subject": "Epic poetry, Italian", "Category": "Text", "EBook-No.": "1012", "Release Date": "Aug 1, 1997", "Copyright Status": "Public domain in the USA.", "Downloads": "671 downloads in the last 30 days.", "Price": "$0.00", "file_link": "https://www.gutenberg.org/files/1012/1012-0.txt", "filename": "Dante Alighieri - La Divina Commedia di Dante"}, {"Author": "Macaulay, Thomas Babington Macaulay, Baron, 1800-1859", "Title": "Lays of Ancient Rome", "Contents": "Horatius -- The Battle of the Lake Regillus -- Virginia -- The Prophecy of Capys.", "Language": "English", "LoC Class": "PR: Language and Literatures: English literature", "Subject": "Rome -- History -- Poetry", "Category": "Text", "EBook-No.": "847", "Release Date": "Jan 21, 2006", "Copyright Status": "Public domain in the USA.", "Downloads": "545 downloads in the last 30 days.", "Price": "$0.00", "file_link": "https://www.gutenberg.org/ebooks/847.txt.utf-8", "filename": "Baron Thomas Babington Macaulay Macaulay - Lays of Ancient Rome"}, {"Author": "Cunningham, Allan, 1784-1842", "Title": "The Complete Works of Robert Burns: Containing his Poems, Songs, and Correspondence.\rWith a New Life of the Poet, and Notices, Critical and Biographical by Allan Cunningham", "Language": "English", "LoC Class": "PR: Language and Literatures: English literature", "Subject": "Poets, Scottish -- 18th century -- Correspondence", "Category": "Text", "EBook-No.": "18500", "Release Date": "Jun 4, 2006", "Copyright Status": "Public domain in the USA.", "Downloads": "534 downloads in the last 30 days.", "Price": "$0.00", "file_link": "https://www.gutenberg.org/ebooks/18500.txt.utf-8", "filename": "Allan Cunningham - The Complete Works of Robert Burns: Containing his Poems, Songs, and Correspondence.\rWith a New Life of the Poet, and Notices, Critical and Biographical by Allan Cunningham"}, {"Editor": "Sharp, Robert, 1851-1932", "Title": "I. Be\u00f3wulf: an Anglo-Saxon poem. II. The fight at Finnsburh: a fragment.", "Language": "Old English", "LoC Class": "PR: Language and Literatures: English literature", "Subject": "Dragons -- Poetry", "Category": "Text", "EBook-No.": "9700", "Release Date": "Jan 1, 2006", "Copyright Status": "Public domain in the USA.", "Downloads": "484 downloads in the last 30 days.", "Price": "$0.00", "file_link": "https://www.gutenberg.org/files/9700/9700-0.txt", "filename": "Robert Sharp - I. Be\u00f3wulf: an Anglo-Saxon poem. II. The fight at Finnsburh: a fragment."}, {"Author": "Horace, 65 BCE-8 BCE", "Title": "The Works of Horace", "Language": "English", "LoC Class": "PA: Language and Literatures: Classical Languages and Literature", "Subject": "Horace -- Translations into English", "Category": "Text", "EBook-No.": "14020", "Release Date": "Nov 11, 2004", "Copyright Status": "Public domain in the USA.", "Downloads": "479 downloads in the last 30 days.", "Price": "$0.00", "file_link": "https://www.gutenberg.org/ebooks/14020.txt.utf-8", "filename": "Horace - The Works of Horace"}, {"Author": "Whitman, Walt, 1819-1892", "Title": "Drum-Taps", "Language": "English", "LoC Class": "PS: Language and Literatures: American and Canadian literature", "Subject": "War poetry, American", "Category": "Text", "EBook-No.": "8801", "Release Date": "Sep 1, 2005", "Copyright Status": "Public domain in the USA.", "Downloads": "418 downloads in the last 30 days.", "Price": "$0.00", "file_link": "https://www.gutenberg.org/ebooks/8801.txt.utf-8", "filename": "Walt Whitman - Drum-Taps"}, {"Author": "Shelley, Percy Bysshe, 1792-1822", "Editor": "Hutchinson, Thomas", "Title": "The Complete Poetical Works of Percy Bysshe Shelley \u2014 Complete", "Language": "English", "LoC Class": "PR: Language and Literatures: English literature", "Subject": "English poetry", "Category": "Text", "EBook-No.": "4800", "Release Date": "Dec 1, 2003", "Copyright Status": "Public domain in the USA.", "Downloads": "397 downloads in the last 30 days.", "Price": "$0.00", "file_link": "https://www.gutenberg.org/ebooks/4800.txt.utf-8", "filename": "Thomas Hutchinson - The Complete Poetical Works of Percy Bysshe Shelley \u2014 Complete"}, {"Translator": "Gummere, Francis Barton, 1855-1919", "Title": "Beowulf", "Language": "English", "LoC Class": "PR: Language and Literatures: English literature", "Subject": "Scandinavia -- Poetry", "Category": "Text", "EBook-No.": "981", "Release Date": "Jul 1, 1997", "Copyright Status": "Public domain in the USA.", "Downloads": "389 downloads in the last 30 days.", "Price": "$0.00", "file_link": "https://www.gutenberg.org/ebooks/981.txt.utf-8", "filename": "Francis Barton Gummere - Beowulf"}, {"Author": "Longfellow, Henry Wadsworth, 1807-1882", "Title": "The Complete Poetical Works of Henry Wadsworth Longfellow", "Language": "English", "LoC Class": "PS: Language and Literatures: American and Canadian literature", "Subject": "American poetry", "Category": "Text", "EBook-No.": "1365", "Release Date": "Jun 1, 1998", "Copyright Status": "Public domain in the USA.", "Downloads": "364 downloads in the last 30 days.", "Price": "$0.00", "file_link": "https://www.gutenberg.org/files/1365/1365-0.txt", "filename": "Henry Wadsworth Longfellow - The Complete Poetical Works of Henry Wadsworth Longfellow"}, {"Author": "Cam\u00f5es, Lu\u00eds de, 1524?-1580", "Title": "Os Lus\u00edadas", "Language": "Portuguese", "LoC Class": "PQ: Language and Literatures: Romance literatures: French, Italian, Spanish, Portuguese", "Subject": "Epic poetry, Portuguese", "Category": "Text", "EBook-No.": "3333", "Release Date": "Jul 1, 2002", "Copyright Status": "Public domain in the USA.", "Downloads": "349 downloads in the last 30 days.", "Price": "$0.00", "file_link": "https://www.gutenberg.org/ebooks/3333.txt.utf-8", "filename": "Lu\u00eds de Cam\u00f5es - Os Lus\u00edadas"}, {"Author": "Byron, George Gordon Byron, Baron, 1788-1824", "Editor": "Coleridge, Ernest Hartley, 1846-1920", "Title": "The Works of Lord Byron. Vol. 5\rPoetry", "Language": "English", "LoC Class": "PR: Language and Literatures: English literature", "Subject": "English drama", "Category": "Text", "EBook-No.": "23475", "Release Date": "Nov 14, 2007", "Copyright Status": "Public domain in the USA.", "Downloads": "346 downloads in the last 30 days.", "Price": "$0.00", "file_link": "https://www.gutenberg.org/files/23475/23475-0.txt", "filename": "Ernest Hartley Coleridge - The Works of Lord Byron. Vol. 5\rPoetry"}, {"Author": "Longfellow, Henry Wadsworth, 1807-1882", "Editor": "Morris, Woodrow W.", "Title": "The Song of Hiawatha", "Language": "English", "LoC Class": "PS: Language and Literatures: American and Canadian literature", "Subject": "Iroquois Indians -- Kings and rulers -- Poetry", "Category": "Text", "EBook-No.": "19", "Release Date": "Jun 1, 2004", "Copyright Status": "Public domain in the USA.", "Downloads": "339 downloads in the last 30 days.", "Price": "$0.00", "file_link": "https://www.gutenberg.org/ebooks/19.txt.utf-8", "filename": "Woodrow W. Morris - The Song of Hiawatha"}, {"Author": "Byron, George Gordon Byron, Baron, 1788-1824", "Editor": "Coleridge, Ernest Hartley, 1846-1920", "Title": "The Works of Lord Byron. Vol. 4", "Language": "English", "LoC Class": "PR: Language and Literatures: English literature", "Subject": "Poetry", "Category": "Text", "EBook-No.": "20158", "Release Date": "Dec 22, 2006", "Copyright Status": "Public domain in the USA.", "Downloads": "322 downloads in the last 30 days.", "Price": "$0.00", "file_link": "https://www.gutenberg.org/files/20158/20158-0.txt", "filename": "Ernest Hartley Coleridge - The Works of Lord Byron. Vol. 4"}, {"Author": "Byron, George Gordon Byron, Baron, 1788-1824", "Editor": "Coleridge, Ernest Hartley, 1846-1920", "Title": "The Works of Lord Byron. Vol. 3", "Language": "English", "LoC Class": "PR: Language and Literatures: English literature", "Subject": "English poetry", "Category": "Text", "EBook-No.": "21811", "Release Date": "Jun 12, 2007", "Copyright Status": "Public domain in the USA.", "Downloads": "278 downloads in the last 30 days.", "Price": "$0.00", "file_link": "https://www.gutenberg.org/files/21811/21811-0.txt", "filename": "Ernest Hartley Coleridge - The Works of Lord Byron. Vol. 3"}]}